Orange3_Replace_Text-0.0.1-py3.9-nspkg.pth
orangecontrib/replace_text/__init__.py
orangecontrib/replace_text/widgets/__init__.py
orangecontrib/replace_text/widgets/owreplace_text.py
orangecontrib/replace_text/widgets/icons/replace_text.svg
Orange3_Replace_Text-0.0.1.dist-info/METADATA
Orange3_Replace_Text-0.0.1.dist-info/WHEEL
Orange3_Replace_Text-0.0.1.dist-info/entry_points.txt
Orange3_Replace_Text-0.0.1.dist-info/namespace_packages.txt
Orange3_Replace_Text-0.0.1.dist-info/top_level.txt
Orange3_Replace_Text-0.0.1.dist-info/RECORD
